dontcryzz/__init__.py
dontcryzz/_aevents.py
dontcryzz/_client.py
dontcryzz/_core.py
dontcryzz/_exception.py
dontcryzz/_message.py
dontcryzz/_objects.py
dontcryzz/_package.py
dontcryzz/_parse_message.py
dontcryzz/_state.py
dontcryzz/_threads.py
dontcryzz/_util.py
dontcryzz/_version.py
dontcryzz/logging.py
dontcryzz/models.py
dontcryzz-1.dist-info/METADATA
dontcryzz-1.dist-info/WHEEL
dontcryzz-1.dist-info/top_level.txt
dontcryzz-1.dist-info/RECORD
