Metadata-Version: 2.4
Name: dontcryzz
Version: 1
Summary: package
Author-email: khah <tranchikhanh209@gmail.com>
License: MIT
Requires-Python: >=3.8
